usf_agents/__init__.py
usf_agents/usfAgent.py
usf_agents/usfMessageHandler.py
usf_agents/usfPlanner.py
usf_agents/examples/data_science_orchestrator.py
usf_agents/examples/incident_response_orchestrator.py
usf_agents/examples/manager_dynamic_orchestrator.py
usf_agents/examples/multi_agent_examples.md
usf_agents/examples/product_launch_orchestrator.py
usf_agents/graph/__init__.py
usf_agents/graph/workflow.py
usf_agents/multi_agent/__init__.py
usf_agents/multi_agent/adapter.py
usf_agents/multi_agent/base.py
usf_agents/multi_agent/bus.py
usf_agents/multi_agent/context.py
usf_agents/multi_agent/registry.py
usf_agents/runtime/safe_seq.py
usf_agents/runtime/validate.py
usf_agents/trace/trace.py
usf_agents/trace/visualize.py
usf_agents/types/__init__.py
usf_agents/types/multi_agent.py
usf_agents-2.2.1.dist-info/licenses/LICENSE
usf_agents-2.2.1.dist-info/METADATA
usf_agents-2.2.1.dist-info/WHEEL
usf_agents-2.2.1.dist-info/top_level.txt
usf_agents-2.2.1.dist-info/RECORD
