Metadata-Version: 2.4
Name: usf-agents
Version: 2.2.1
Summary: A lightweight multi-agent orchestration framework with better control, easy to use for complex to simple use cases. Developer friendly with more visibility and supports all models with OpenAI compatible API.
Author: UltraSafe AI Team
License: USF Agents SDK License
Project-URL: Homepage, https://us.inc
Project-URL: Repository, https://github.com/UltraSafeAI/usf-agents-python
Project-URL: Documentation, https://us.inc/docs
Project-URL: Bug Reports, https://github.com/UltraSafeAI/usf-agents-python/issues
Keywords: multi-agent,orchestration,framework,lightweight,agent,developer-friendly,visibility,control,complex-usecase,simple-usecase,all-models,openai-compatible,llm,ai-agent,tool-calling,streaming,usf,planning,UltraSafe,UltraSafe AI,usf-agents
Classifier: Development Status :: 5 - Production/Stable
Classifier: Intended Audience :: Developers
Classifier: License :: Other/Proprietary License
Classifier: Operating System :: OS Independent
Classifier: Programming Language :: Python :: 3
Classifier: Programming Language :: Python :: 3.8
Classifier: Programming Language :: Python :: 3.9
Classifier: Programming Language :: Python :: 3.10
Classifier: Programming Language :: Python :: 3.11
Classifier: Programming Language :: Python :: 3.12
Classifier: Topic :: Software Development :: Libraries :: Python Modules
Classifier: Topic :: Scientific/Engineering :: Artificial Intelligence
Requires-Python: >=3.8
License-File: LICENSE
Requires-Dist: openai>=1.0.0
Requires-Dist: aiohttp>=3.8.0
Dynamic: license-file
Dynamic: requires-python
